TGConvertor/__init__.py
TGConvertor/__main__.py
TGConvertor/api.py
TGConvertor/data_center.py
TGConvertor/exceptions.py
TGConvertor/manager.py
TGConvertor/sessions/__init__.py
TGConvertor/sessions/tdata.py
TGConvertor/sessions/tele.py
TGConvertor/sessions/pyro/__init__.py
TGConvertor/sessions/pyro/kuri.py
TGConvertor/sessions/pyro/pyro.py
tgconvertor-0.1.4.dist-info/licenses/LICENSE
tgconvertor-0.1.4.dist-info/METADATA
tgconvertor-0.1.4.dist-info/WHEEL
tgconvertor-0.1.4.dist-info/entry_points.txt
tgconvertor-0.1.4.dist-info/top_level.txt
tgconvertor-0.1.4.dist-info/RECORD
