Metadata-Version: 2.4
Name: tgconvertor
Version: 0.1.4
Summary: This module is small util for easy converting Telegram sessions to various formats.
Author-email: Назар <nazar.fedorowych@gmail.com>
License: MIT
Project-URL: Homepage, https://github.com/nazar220160/TGConvertor
Project-URL: Repository, https://github.com/nazar220160/TGConvertor.git
Project-URL: Issues, https://github.com/nazar220160/TGConvertor/issues
Project-URL: Changelog, https://github.com/nazar220160/TGConvertor/releases
Keywords: telegram,session,converter,telethon,pyrogram
Classifier: Development Status :: 4 - Beta
Classifier: Intended Audience :: Developers
Classifier: License :: OSI Approved :: MIT License
Classifier: Programming Language :: Python :: 3
Classifier: Programming Language :: Python :: 3.10
Classifier: Programming Language :: Python :: 3.11
Classifier: Programming Language :: Python :: 3.12
Classifier: Programming Language :: Python :: 3.13
Classifier: Topic :: Software Development :: Libraries :: Python Modules
Classifier: Topic :: Communications :: Chat
Requires-Python: <3.14,>=3.10
License-File: LICENSE
Requires-Dist: typer>=0.9.0
Requires-Dist: rich>=13.0.0
Requires-Dist: typing-extensions>=4.0.0
Requires-Dist: aiosqlite
Provides-Extra: pyrogram
Requires-Dist: pyrogram; extra == "pyrogram"
Provides-Extra: kurigram
Requires-Dist: kurigram; extra == "kurigram"
Provides-Extra: tdata
Requires-Dist: opentele; extra == "tdata"
Dynamic: license-file
